solana/__init__.py
solana/rpc/__init__.py
solana/rpc/types/__init__.py
semantic_types-0.1.5.dist-info/LICENSE
semantic_types-0.1.5.dist-info/METADATA
semantic_types-0.1.5.dist-info/WHEEL
semantic_types-0.1.5.dist-info/top_level.txt
semantic_types-0.1.5.dist-info/RECORD
