Metadata-Version: 2.2
Name: semantic-types
Version: 0.1.5
Summary: Semantic Typing
Author-email: Cappership <cappership@proton.me>
Project-URL: Homepage, https://www.exakat.io/en/semantic-typing
Keywords: semantics
Classifier: Intended Audience :: Developers
Classifier: License :: OSI Approved :: MIT License
Classifier: Natural Language :: English
Classifier: Programming Language :: Python :: 3.8
Classifier: Programming Language :: Python :: 3.9
Classifier: Programming Language :: Python :: 3.10
Classifier: Programming Language :: Python :: 3.11
Classifier: Programming Language :: Python :: 3.12
Classifier: Programming Language :: Python :: 3.13
Requires-Python: >=3.8
License-File: LICENSE
